fortecubeview/__init__.py
fortecubeview/atom_data.py
fortecubeview/cube_file.py
fortecubeview/cube_viewer.py
fortecubeview/fortecubeview.py
fortecubeview/mol_viewer.py
fortecubeview/py3js_renderer.py
fortecubeview/vib_viewer.py
fortecubeview-0.2.3.dist-info/LICENSE
fortecubeview-0.2.3.dist-info/METADATA
fortecubeview-0.2.3.dist-info/WHEEL
fortecubeview-0.2.3.dist-info/top_level.txt
fortecubeview-0.2.3.dist-info/RECORD
