Metadata-Version: 2.1
Name: fortecubeview
Version: 0.2.3
Summary: A geometry, cube file, and vibrational modes viewer for Psi4 and Forte
Home-page: https://github.com/evangelistalab/fortecubeview
Author: Francesco Evangelista
Author-email: 
License: UNKNOWN
Platform: UNKNOWN
Classifier: Programming Language :: Python :: 3
Classifier: License :: OSI Approved :: MIT License
Classifier: Operating System :: OS Independent
Requires-Python: >=3.6
License-File: LICENSE
